{
  "filmes": [
    {
      "id": 1,
      "title": "Anaconda",
      "descricao": "Uma cobra grande comendo todo mundo na floresta",
      "author": "João",
      "avaliacao": "filme chato, só tem uma cobra grande que come todo mundo",
      "cartaz": "https://media.fstatic.com/tLWMRFJj9rXy8qmzclVxgqndsDY=/210x312/smart/filters:format(webp)/media/movies/covers/2011/11/a01a5d9340e102232fc6276b4009154c.jpg",
      "genero": "Ação",
      "cor": "laranja",
      "vizualiado": "",
      "nota": 0
    },
    {
      "id": 2,
      "title": "shrek 2",
      "descricao": "bom filme",
      "author": "João",
      "avaliacao": "10",
      "cartaz": "https://upload.wikimedia.org/wikipedia/pt/7/78/Shrek_2_Poster.jpg",
      "genero": "Animação",
      "cor": "verde",
      "vizualiado": "1",
      "nota": 2
    },
    {
      "id": 3,
      "title": "homem aranha",
      "descricao": "Filme do espetacular homem aranha e suas aventuras com seus amigos",
      "author": "Alan Ferreira",
      "avaliacao": "Exelente",
      "cartaz": "https://sm.ign.com/ign_br/screenshot/default/image002_uuhb.jpg",
      "genero": "Animação",
      "cor": "vermelha",
      "vizualiado": "5",
      "nota": 6
    },
    {
      "id": 4,
      "title": "Noiva cadaver ",
      "descricao": "Infantil",
      "author": "Daniel",
      "avaliacao": "Filme sobre uma historia de romance",
      "cartaz": "https://i.pinimg.com/236x/ae/23/5e/ae235ec569716209cb13e2e4111a38d4--corpse-bride-movie-tim-burton-corpse-bride.jpg",
      "genero": "Livre",
      "cor": "verde",
      "vizualiado": "Quero",
      "nota": 2
    },
    {
      "id": 5,
      "title": "Noiva cadaver ",
      "descricao": "Infantil",
      "author": "Daniel",
      "avaliacao": "Filme sobre uma historia de romance",
      "cartaz": "https://i.pinimg.com/236x/ae/23/5e/ae235ec569716209cb13e2e4111a38d4--corpse-bride-movie-tim-burton-corpse-bride.jpg",
      "genero": "Livre",
      "cor": "verde",
      "vizualiado": "Quero",
      "nota": 2
    }
  ]
}